libdash/_dash.py
libdash/ast.py
libdash/parser.py
libdash/libdash.so
libdash/printer.py
libdash/__init__.py
libdash-0.3.1.dist-info/top_level.txt
libdash-0.3.1.dist-info/WHEEL
libdash-0.3.1.dist-info/METADATA
libdash-0.3.1.dist-info/RECORD
libdash-0.3.1.dist-info/COPYING
