Metadata-Version: 2.1
Name: libdash
Version: 0.3.1
Summary: Bindings for the dash shell as a library
Author-email: Michael Greenberg <michael@greenberg.science>
License: Copyright (c) 1989-1994
Project-URL: Homepage, https://github.com/mgree/libdash
Project-URL: Bug Tracker, https://github.com/mgree/libdash/issues
Classifier: Programming Language :: Python :: 3
Classifier: Topic :: System :: System Shells
Classifier: License :: OSI Approved :: MIT License
Classifier: Operating System :: POSIX
Requires-Python: >=3.7
